Metadata-Version: 2.1
Name: zeppelin-pyclient
Version: 0.0.2
Summary: zeppelin pyclient
Home-page: https://github.com/xzregg/zeppelin-pyclient.git
Author: xzregg
Author-email: xzregg@gmail.com
License: UNKNOWN
Platform: UNKNOWN
Classifier: Programming Language :: Python :: 3
Classifier: License :: OSI Approved :: MIT License
Classifier: Operating System :: OS Independent
Requires-Python: >=3.6
